betterproto/__init__.py
betterproto/casing.py
betterproto/plugin.py
betterproto/py.typed
betterproto/utils.py
betterproto/templates/template.py
betterproto_twirp-1.2.16.dist-info/METADATA
betterproto_twirp-1.2.16.dist-info/WHEEL
betterproto_twirp-1.2.16.dist-info/entry_points.txt
betterproto_twirp-1.2.16.dist-info/top_level.txt
betterproto_twirp-1.2.16.dist-info/RECORD
