Metadata-Version: 2.1
Name: betterproto-twirp
Version: 1.2.16
Summary: A better Protobuf / Twirp generator & library
Home-page: http://github.com/danielgtaylor/python-betterproto
Author: lvhaitao, yunshu
Author-email: xiewangming@bilibili.com
License: MIT
Platform: UNKNOWN
Requires-Python: >=3.6
Requires-Dist: grpclib
Requires-Dist: stringcase
Requires-Dist: requests
Requires-Dist: python-box
Requires-Dist: jsonpath-rw
Requires-Dist: betterproto-twirp[compiler]
Requires-Dist: dataclasses ; python_version < "3.7"
Requires-Dist: backports-datetime-fromisoformat ; python_version < "3.7"
Provides-Extra: compiler
Requires-Dist: black ; extra == 'compiler'
Requires-Dist: jinja2 ; extra == 'compiler'
Requires-Dist: protobuf ; extra == 'compiler'
